LICENSE.md
README.md
pyproject.toml
aviary/__init__.py
aviary/py.typed
aviary/_cli/__init__.py
aviary/_cli/cli.py
aviary/_cli/templates.py
aviary/_functional/__init__.py
aviary/_functional/tile/__init__.py
aviary/_functional/tile/tile_fetcher.py
aviary/_functional/tile/tiles_exporter.py
aviary/_functional/tile/tiles_processor.py
aviary/_functional/utils/__init__.py
aviary/_functional/utils/coordinates_filter.py
aviary/_functional/vector/__init__.py
aviary/_functional/vector/vector_exporter.py
aviary/_functional/vector/vector_loader.py
aviary/_functional/vector/vector_processor.py
aviary/_utils/__init__.py
aviary/_utils/plugins.py
aviary/_utils/validators.py
aviary/core/__init__.py
aviary/core/bounding_box.py
aviary/core/channel.py
aviary/core/enums.py
aviary/core/exceptions.py
aviary/core/grid.py
aviary/core/tiles.py
aviary/core/type_aliases.py
aviary/core/vector.py
aviary/core/vector_layer.py
aviary/pipeline/__init__.py
aviary/pipeline/pipeline.py
aviary/tile/__init__.py
aviary/tile/tile_fetcher.py
aviary/tile/tile_loader.py
aviary/tile/tile_set.py
aviary/tile/tiles_exporter.py
aviary/tile/tiles_processor.py
aviary/utils/__init__.py
aviary/utils/coordinates_filter.py
aviary/vector/__init__.py
aviary/vector/vector_exporter.py
aviary/vector/vector_loader.py
aviary/vector/vector_processor.py
geospaitial_lab_aviary.egg-info/PKG-INFO
geospaitial_lab_aviary.egg-info/SOURCES.txt
geospaitial_lab_aviary.egg-info/dependency_links.txt
geospaitial_lab_aviary.egg-info/entry_points.txt
geospaitial_lab_aviary.egg-info/requires.txt
geospaitial_lab_aviary.egg-info/top_level.txt