Metadata-Version: 2.4
Name: geospaitial-lab-aviary
Version: 1.1.0
Summary: Pythonic framework for AI inference on geospatial data
Author-email: Marius Maryniak <marius.maryniak@w-hs.de>
Maintainer-email: Marius Maryniak <marius.maryniak@w-hs.de>, Alexander Roß <alexander.ross@w-hs.de>, Stefan Küpper <stefan.kuepper@w-hs.de>
License: GPL-3.0
Project-URL: Homepage, https://www.github.com/geospaitial-lab/aviary
Project-URL: Documentation, https://geospaitial-lab.github.io/aviary
Classifier: License :: OSI Approved :: GNU General Public License v3 (GPLv3)
Classifier: Operating System :: OS Independent
Classifier: Programming Language :: Python
Classifier: Programming Language :: Python :: 3
Classifier: Programming Language :: Python :: 3.10
Classifier: Programming Language :: Python :: 3.11
Classifier: Programming Language :: Python :: 3.12
Classifier: Topic :: Scientific/Engineering :: Artificial Intelligence
Classifier: Topic :: Scientific/Engineering :: GIS
Requires-Python: >=3.10
License-File: LICENSE.md
Requires-Dist: geopandas>=1.1.0
Requires-Dist: loguru>=0.7.0
Requires-Dist: numpy>=2.0.0
Requires-Dist: pydantic>=2.9.0
Requires-Dist: rasterio>=1.4.0
Requires-Dist: requests>=2.32.0
Requires-Dist: rich>=13.9.0
Requires-Dist: shapely>=2.0.4
Provides-Extra: cli
Requires-Dist: pyperclip>=1.9.0; extra == "cli"
Requires-Dist: pyyaml>=6.0.1; extra == "cli"
Requires-Dist: typer>=0.16.0; extra == "cli"
Provides-Extra: all
Requires-Dist: pyperclip>=1.9.0; extra == "all"
Requires-Dist: pyyaml>=6.0.1; extra == "all"
Requires-Dist: typer>=0.16.0; extra == "all"
Dynamic: license-file
